ftlengine-0.1.11.dist-info/METADATA
ftlengine-0.1.11.dist-info/RECORD
ftlengine-0.1.11.dist-info/WHEEL
ftlengine-0.1.11.dist-info/entry_points.txt
ftlengine-0.1.11.dist-info/top_level.txt
src/__init__.py
src/config.py
src/constants.py
src/exceptions.py
src/version.py
src/cli/__init__.py
src/cli/alias_group.py
src/cli/argument_types.py
src/cli/colors.py
src/cli/progress_printer.py
src/cli/spell.py
src/cli/table.py
src/cli/tasks.py
src/containers/container.py
src/containers/formation.py
src/containers/graph.py
src/containers/profile.py
src/containers/volumes.py
src/docker/build.py
src/docker/hosts.py
src/docker/images.py
src/docker/introspect.py
src/docker/io.py
src/docker/runner.py
src/docker/seedship.py
src/exams/doctor_connectivity.py
src/exams/doctor_docker_mac.py
src/exams/doctor_time.py
src/plugins/attach.py
src/plugins/aws.py
src/plugins/base.py
src/plugins/boot.py
src/plugins/build.py
src/plugins/build_scripts.py
src/plugins/chart.py
src/plugins/container.py
src/plugins/create.py
src/plugins/doctor.py
src/plugins/domain_name.py
src/plugins/gc.py
src/plugins/get_gateway_ip.py
src/plugins/help.py
src/plugins/hosts.py
src/plugins/images.py
src/plugins/jump.py
src/plugins/legacy_env.py
src/plugins/mounts.py
src/plugins/plugin_config.py
src/plugins/profile.py
src/plugins/ps.py
src/plugins/registry.py
src/plugins/run.py
src/plugins/system.py
src/plugins/tail.py
src/plugins/upgrade.py
src/plugins/volume.py
src/plugins/waits.py
src/utils/functional.py
src/utils/humanize.py
src/utils/net.py
src/utils/sorting.py
src/utils/threading.py
