Metadata-Version: 2.1
Name: ftlengine
Version: 0.1.11
Summary: A Docker based development and deployment engine
Home-page: https://github.com/Jakob-Daugherty/ftlengine
Author: Jakob Daugherty
Author-email: jakob.daugherty@quarkworks.co
License: UNKNOWN
Platform: UNKNOWN
Classifier: Programming Language :: Python :: 3
Classifier: License :: OSI Approved :: MIT License
Classifier: Operating System :: OS Independent
Classifier: Intended Audience :: Developers
Classifier: Development Status :: 2 - Pre-Alpha
Requires-Python: >=3.6
Requires-Dist: attrs
Requires-Dist: boto3
Requires-Dist: botocore
Requires-Dist: click
Requires-Dist: docker
Requires-Dist: dockerpty
Requires-Dist: ntplib
Requires-Dist: PyYAML
Requires-Dist: requests
Requires-Dist: scandir
Requires-Dist: six
Requires-Dist: urllib3 (==1.26.7)
